pyStuffing/__init__.py
pyStuffing/bitStuffing.py
pyStuffing/byteStuffing.py
pyStuffing/cls.py
pyStuffing-0.0.4.dist-info/LICENSE
pyStuffing-0.0.4.dist-info/METADATA
pyStuffing-0.0.4.dist-info/WHEEL
pyStuffing-0.0.4.dist-info/top_level.txt
pyStuffing-0.0.4.dist-info/RECORD
