Metadata-Version: 2.1
Name: pyStuffing
Version: 0.0.4
Summary: A Python package for performing Bit Stuffing and Byte Stuffing operations
Home-page: https://github.com/fazalfarhan01/pyStuffing
Author: Mohamed Farhan Fazal
Author-email: fazal.farhan@gmail.com
License: UNKNOWN
Project-URL: Bug Tracker, https://github.com/fazalfarhan01/pyStuffing/issues
Platform: UNKNOWN
Classifier: Programming Language :: Python :: 3
Classifier: License :: OSI Approved :: MIT License
Classifier: Operating System :: OS Independent
Requires-Python: >=3.6
Requires-Dist: colorama (>=0.4.4)
